pyquick/__init__.py
pyquick/args.py
pyquick/main.py
pyquick/proj.py
pyquick/version.py
pyquick/templates/Dockerfile-dev.jinja2
pyquick/templates/LICENSE.jinja2
pyquick/templates/MANIFEST.in
pyquick/templates/gitignore
pyquick/templates/requirements-dev.txt
pyquick/templates/requirements.txt
pyquick/templates/test_simple.py.jinja2
pyquick/templates/version.py.jinja2
pyquick/templates/app.t/Dockerfile.jinja2
pyquick/templates/app.t/Makefile.jinja2
pyquick/templates/app.t/README.md.jinja2
pyquick/templates/app.t/docker-compose.yml.jinja2
pyquick/templates/app.t/main.py.jinja2
pyquick/templates/app.t/setup.py.jinja2
pyquick/templates/lib.t/Makefile.jinja2
pyquick/templates/lib.t/README.md.jinja2
pyquick/templates/lib.t/docker-compose.yml.jinja2
pyquick/templates/lib.t/setup.py.jinja2
pyquick/templates/vscode/install-vscode-extensions.sh
pyquick/templates/vscode/settings.json
pyquick/templates/vscode/.ropeproject/config.py
pyquick/templates/vscode/.ropeproject/objectdb
pyquick-0.0.1a6.dist-info/LICENSE
pyquick-0.0.1a6.dist-info/METADATA
pyquick-0.0.1a6.dist-info/WHEEL
pyquick-0.0.1a6.dist-info/entry_points.txt
pyquick-0.0.1a6.dist-info/top_level.txt
pyquick-0.0.1a6.dist-info/RECORD
