Metadata-Version: 2.1
Name: pyquick
Version: 0.0.1a6
Summary: A Python Demo
Home-page: https://github.com/jevyzhu/pyquick
Author: jingwei zhu
Author-email: jingweizhucn@126.com
License: UNKNOWN
Platform: UNKNOWN
Classifier: Programming Language :: Python :: 3
Classifier: License :: OSI Approved :: MIT License
Classifier: Operating System :: OS Independent
Requires-Python: >=3.7
Requires-Dist: jinja2 (>=2.11.2)
